<annotation>
	<folder>training_set_finetuning</folder>
	<filename>b-e-l-2 (425).jpg</filename>
	<path>./training/data/himax/testing/testset/b-e-l-2 (425).jpg</path>
	<source>
		<database>Unknown</database>
	</source>
	<size>
		<width>324</width>
		<height>244</height>
		<depth>1</depth>
	</size>
	<segmented>0</segmented>
	<object>
		<name>Bottle</name>
		<pose>Unspecified</pose>
		<truncated>0</truncated>
		<difficult>0</difficult>
		<bndbox>
			<xmin>56</xmin>
			<ymin>49</ymin>
			<xmax>98</xmax>
			<ymax>211</ymax>
		</bndbox>
	</object>
	<object>
		<name>Bottle</name>
		<pose>Unspecified</pose>
		<truncated>0</truncated>
		<difficult>0</difficult>
		<bndbox>
			<xmin>144</xmin>
			<ymin>126</ymin>
			<xmax>169</xmax>
			<ymax>207</ymax>
		</bndbox>
	</object>
	<object>
		<name>Tin can</name>
		<pose>Unspecified</pose>
		<truncated>1</truncated>
		<difficult>0</difficult>
		<bndbox>
			<xmin>196</xmin>
			<ymin>152</ymin>
			<xmax>231</xmax>
			<ymax>244</ymax>
		</bndbox>
	</object>
</annotation>
